.hgignore
GNUmakefile
INSTALL
LICENSE
MANIFEST.in
NEWS
README.rst
cheat.el
coding.py
distribute_setup.py
setup.cfg
setup.py
tests.py
coding.egg-info/PKG-INFO
coding.egg-info/SOURCES.txt
coding.egg-info/dependency_links.txt
coding.egg-info/top_level.txt
docs/Makefile
docs/source/conf.py
docs/source/index.rst