Metadata-Version: 1.1
Name: coding
Version: 0.002
Summary: An answer to the question of python enums.
Home-page: http://bitbucket.org/krp/coding
Author: K. Richard Pixley
Author-email: rich@noir.com
License: MIT
Keywords: enum coding
Platform: UNKNOWN
Classifier: Development Status :: 3 - Alpha
Classifier: Intended Audience :: Developers
Classifier: License :: OSI Approved :: MIT License
Classifier: Natural Language :: English
Classifier: Operating System :: OS Independent
Classifier: Programming Language :: Python
Classifier: Programming Language :: Python :: 2.6
Classifier: Programming Language :: Python :: 2.7
Classifier: Programming Language :: Python :: 3.0
Classifier: Programming Language :: Python :: 3.1
Classifier: Programming Language :: Python :: 3.2
Classifier: Topic :: Software Development :: Libraries :: Python Modules
Provides: coding
